similarity_checker/__init__.py
similarity_checker/analysis_matcher.py
similarity_checker/graph_matcher.py
similarity_checker/numeric_matcher.py
llm_similarity_checker-0.1.4.dist-info/METADATA
llm_similarity_checker-0.1.4.dist-info/WHEEL
llm_similarity_checker-0.1.4.dist-info/top_level.txt
llm_similarity_checker-0.1.4.dist-info/RECORD
