Metadata-Version: 2.1
Name: llm_similarity_checker
Version: 0.1.4
Summary: The SimilarityChecker module determines the similarity between two items.
Home-page: https://github.com/yewleongtoh/similarity_checker
Author: Toh Yew Leong
Author-email: yewleongtoh@gmail.com
Classifier: Programming Language :: Python :: 3
Classifier: Operating System :: OS Independent
Requires-Python: >=3.7
Requires-Dist: transformers ==4.42.3
Requires-Dist: scipy ==1.14.0
Requires-Dist: joblib ==1.4.2
Requires-Dist: torch ==2.3.1
